.gitignore
.requires
.test-requires
LICENSE
MANIFEST.in
README.rst
setup.py
tox.ini
bin/dump_limits
bin/remote_daemon
bin/setup_limits
tests/__init__.py
tests/db_fixture.py
tests/test_config.py
tests/test_control.py
tests/test_database.py
tests/test_limits.py
tests/test_middleware.py
tests/test_remote.py
tests/test_tools.py
tests/test_utils.py
turnstile/__init__.py
turnstile/config.py
turnstile/control.py
turnstile/database.py
turnstile/limits.py
turnstile/middleware.py
turnstile/remote.py
turnstile/tools.py
turnstile/utils.py
turnstile.egg-info/PKG-INFO
turnstile.egg-info/SOURCES.txt
turnstile.egg-info/dependency_links.txt
turnstile.egg-info/entry_points.txt
turnstile.egg-info/requires.txt
turnstile.egg-info/top_level.txt