Metadata-Version: 1.0
Name: turnstile
Version: 0.6.1
Summary: Distributed rate-limiting middleware
Home-page: https://github.com/klmitch/turnstile
Author: Kevin L. Mitchell
Author-email: kevin.mitchell@rackspace.com
License: Apache License (2.0)
Platform: UNKNOWN
Classifier: Development Status :: 4 - Beta
Classifier: Environment :: Web Environment
Classifier: Framework :: Paste
Classifier: Intended Audience :: System Administrators
Classifier: License :: OSI Approved :: Apache Software License
Classifier: Programming Language :: Python
Classifier: Topic :: Internet :: WWW/HTTP :: WSGI :: Middleware
